erniebot_agent/__init__.py
erniebot_agent/version.py
erniebot_agent/agents/__init__.py
erniebot_agent/agents/agent.py
erniebot_agent/agents/base.py
erniebot_agent/agents/function_agent.py
erniebot_agent/agents/function_agent_with_retrieval.py
erniebot_agent/agents/schema.py
erniebot_agent/agents/callback/__init__.py
erniebot_agent/agents/callback/callback_manager.py
erniebot_agent/agents/callback/default.py
erniebot_agent/agents/callback/event.py
erniebot_agent/agents/callback/handlers/__init__.py
erniebot_agent/agents/callback/handlers/base.py
erniebot_agent/agents/callback/handlers/logging_handler.py
erniebot_agent/agents/mixins/__init__.py
erniebot_agent/agents/mixins/gradio_mixin.py
erniebot_agent/chat_models/__init__.py
erniebot_agent/chat_models/base.py
erniebot_agent/chat_models/erniebot.py
erniebot_agent/extensions/langchain/chat_models/__init__.py
erniebot_agent/extensions/langchain/chat_models/erniebot.py
erniebot_agent/extensions/langchain/embeddings/__init__.py
erniebot_agent/extensions/langchain/embeddings/ernie.py
erniebot_agent/extensions/langchain/llms/__init__.py
erniebot_agent/extensions/langchain/llms/erniebot.py
erniebot_agent/file/__init__.py
erniebot_agent/file/base.py
erniebot_agent/file/file_manager.py
erniebot_agent/file/file_registry.py
erniebot_agent/file/global_file_manager_handler.py
erniebot_agent/file/local_file.py
erniebot_agent/file/protocol.py
erniebot_agent/file/remote_file.py
erniebot_agent/memory/__init__.py
erniebot_agent/memory/base.py
erniebot_agent/memory/limit_tokens_memory.py
erniebot_agent/memory/messages.py
erniebot_agent/memory/sliding_window_memory.py
erniebot_agent/memory/whole_memory.py
erniebot_agent/prompt/__init__.py
erniebot_agent/prompt/base.py
erniebot_agent/prompt/prompt_template.py
erniebot_agent/retrieval/__init__.py
erniebot_agent/retrieval/baizhong_search.py
erniebot_agent/retrieval/document.py
erniebot_agent/tools/__init__.py
erniebot_agent/tools/baizhong_tool.py
erniebot_agent/tools/base.py
erniebot_agent-0.5.2.dist-info/METADATA
erniebot_agent-0.5.2.dist-info/WHEEL
erniebot_agent-0.5.2.dist-info/entry_points.txt
erniebot_agent-0.5.2.dist-info/top_level.txt
erniebot_agent-0.5.2.dist-info/RECORD
