Metadata-Version: 2.1
Name: erniebot-agent
Version: 0.5.2
Summary: Python library for the ERNIE Bot Agent
Classifier: Programming Language :: Python
Requires-Python: >=3.8
Requires-Dist: aiohttp
Requires-Dist: anyio
Requires-Dist: asyncio-atexit
Requires-Dist: erniebot
Requires-Dist: jinja2
Requires-Dist: langchain
Requires-Dist: openapi-spec-validator
Requires-Dist: tqdm
Requires-Dist: typing-extensions
Requires-Dist: pydantic (>=2)
Requires-Dist: PyYAML
Provides-Extra: all
Requires-Dist: erniebot-agent[gradio] ; extra == 'all'
Requires-Dist: erniebot-agent[jinja2] ; extra == 'all'
Provides-Extra: gradio
Requires-Dist: gradio (>=3.48) ; extra == 'gradio'
Provides-Extra: jinja2
Requires-Dist: jinja2 ; extra == 'jinja2'
